hipal_mixin_scrud/__init__.py
hipal_mixin_scrud/mixin.py
hipal_mixin_scrud/crud/__init__.py
hipal_mixin_scrud/crud/generator.py
hipal_mixin_scrud/crud/mixin_list.py
hipal_mixin_scrud/enums/__init__.py
hipal_mixin_scrud/enums/operators.py
hipal_mixin_scrud/enums/sorts.py
hipal_mixin_scrud/schemas/__init__.py
hipal_mixin_scrud/schemas/paginate_params.py
hipal_mixin_scrud/schemas/pagination_base.py
hipal_mixin_scrud/tests/__init__.py
hipal_mixin_scrud/tests/test_mixin_paginate.py
hipal_mixin_scrud/tests/factory_test/__init__.py
hipal_mixin_scrud/tests/factory_test/person.py
hipal_mixin_scrud-1.0.7.dist-info/METADATA
hipal_mixin_scrud-1.0.7.dist-info/WHEEL
hipal_mixin_scrud-1.0.7.dist-info/top_level.txt
hipal_mixin_scrud-1.0.7.dist-info/RECORD
